sid/__init__.py
sid/cli.py
sid/index.py
sid/objects.py
sid/refs.py
sid/repo.py
sid_vcs-0.2.0.dist-info/licenses/LICENSE
sid_vcs-0.2.0.dist-info/METADATA
sid_vcs-0.2.0.dist-info/WHEEL
sid_vcs-0.2.0.dist-info/entry_points.txt
sid_vcs-0.2.0.dist-info/top_level.txt
sid_vcs-0.2.0.dist-info/RECORD
