Metadata-Version: 2.4
Name: sid-vcs
Version: 0.2.0
Summary: SID — an educational Git-like VCS
Author-email: Siddhant Gangawane <siddhantgangawane335@email.com>
License: MIT
Requires-Python: >=3.8
License-File: LICENSE
Dynamic: license-file
